calliope/__init__.py
calliope/chemistry.py
calliope/constants.py
calliope/oxygen_fugacity.py
calliope/solubility.py
calliope/solve.py
calliope/structure.py
fwl_calliope-25.5.4.dist-info/licenses/LICENSE.txt
fwl_calliope-25.5.4.dist-info/METADATA
fwl_calliope-25.5.4.dist-info/WHEEL
fwl_calliope-25.5.4.dist-info/top_level.txt
fwl_calliope-25.5.4.dist-info/RECORD
