Metadata-Version: 2.4
Name: fwl-calliope
Version: 25.5.4
Summary: Planetary accretion and volatile delivery model
Author: Harrison Nicholls, email = harrison.nicholls@physics.ox.ac.uk
License: Apache 2.0 License
Project-URL: homepage, https://github.com/FormingWorlds/CALLIOPE
Project-URL: issues, https://github.com/FormingWorlds/CALLIOPE/issues
Project-URL: documentation, https://fwl-proteus.readthedocs.io
Project-URL: changelog, https://github.com/FormingWorlds/CALLIOPE/releases
Keywords: Astronomy,Exoplanets,Model-coupling
Classifier: Development Status :: 3 - Alpha
Classifier: Intended Audience :: Science/Research
Classifier: License :: OSI Approved :: Apache Software License
Classifier: Natural Language :: English
Classifier: Operating System :: OS Independent
Classifier: Programming Language :: Python :: 3
Classifier: Programming Language :: Python :: 3.11
Classifier: Programming Language :: Python :: 3.12
Classifier: Programming Language :: Python :: 3.13
Classifier: Topic :: Scientific/Engineering :: Astronomy
Requires-Python: >=3.11
License-File: LICENSE.txt
Requires-Dist: matplotlib
Requires-Dist: numpy
Requires-Dist: scipy
Requires-Dist: cmcrameri
Provides-Extra: develop
Requires-Dist: bump-my-version; extra == "develop"
Requires-Dist: coverage[toml]; extra == "develop"
Requires-Dist: pip-tools; extra == "develop"
Requires-Dist: pytest>=8.1; extra == "develop"
Requires-Dist: pre-commit; extra == "develop"
Requires-Dist: ruff; extra == "develop"
Provides-Extra: docs
Requires-Dist: markdown-include; extra == "docs"
Requires-Dist: mkdocs; extra == "docs"
Requires-Dist: mkdocs-material; extra == "docs"
Requires-Dist: mkdocstrings[python]; extra == "docs"
Dynamic: license-file
